{"table_of_player": {"1": {"name": "dupont", "first_name": "antoine", "date_of_birth": "11/22/90", "gender": "homme", "rang": 7, "number_of_point": 0}, "2": {"name": "dupont", "first_name": "antoine", "date_of_birth": "11/22/90", "gender": "homme", "rang": 7, "number_of_point": 0}, "3": {"name": "dupont", "first_name": "antoine", "date_of_birth": "11/22/90", "gender": "homme", "rang": 7, "number_of_point": 0}, "4": {"name": "dupont", "first_name": "antoine", "date_of_birth": "11/22/90", "gender": "homme", "rang": 7, "number_of_point": 0}, "5": {"name": "oblin", "first_name": "guillaume", "date_of_birth": "26-04-1988", "gender": 1, "rang": null, "number_of_point": 0}, "6": {"name": "hhhhhhh", "first_name": "ffffff", "date_of_birth": "11-11-2020", "gender": 0, "rang": null, "number_of_point": 0}, "7": {"name": "aa", "first_name": "aa", "date_of_birth": "13-12-2020", "gender": 1, "rang": null, "number_of_point": 0}, "8": {"name": "azaz", "first_name": "azaz", "date_of_birth": "11-05-2020", "gender": 1, "rang": null, "number_of_point": 0}, "9": {"name": "toto", "first_name": "aaa", "date_of_birth": "20-05-2021", "gender": 1, "rang": null, "number_of_point": 0}, "10": {"name": "shshsy", "first_name": "gttsy", "date_of_birth": "20-09-1988", "gender": 1, "rang": null, "number_of_point": 0}, "11": {"name": "gtth", "first_name": "hdjju", "date_of_birth": "29-03-2011", "gender": 0, "rang": null, "number_of_point": 0}, "12": {"name": "sjthprut", "first_name": "gtupiut", "date_of_birth": "10-02-1988", "gender": 0, "rang": null, "number_of_point": 0}, "13": {"name": "ippiurgg", "first_name": "rtyudu", "date_of_birth": "10-12-1099", "gender": 0, "rang": null, "number_of_point": 0}, "14": {"name": "dupont", "first_name": "antoine", "date_of_birth": "11/22/90", "gender": "homme", "rang": 7, "number_of_point": 0}, "15": {"name": "fytrdtrdut", "first_name": "hhguu", "date_of_birth": "11-02-1999", "gender": 0, "rang": null, "number_of_point": 0}, "16": {"name": "hlyguyl", "first_name": "jhu", "date_of_birth": "11-11-2022", "gender": 0, "rang": null, "number_of_point": 0}, "17": {"name": "m", "first_name": "m", "date_of_birth": "11-02-1231", "gender": 0, "rang": null, "number_of_point": 0}, "18": {"name": "q", "first_name": "q", "date_of_birth": "11-11-2022", "gender": 0, "rang": null, "number_of_point": 0}, "19": {"name": "d", "first_name": "d", "date_of_birth": "11-02-1988", "gender": 0, "rang": null, "number_of_point": 0}, "20": {"name": "z", "first_name": "z", "date_of_birth": "11-11-2525", "gender": 0, "rang": null, "number_of_point": 0}, "21": {"name": "e", "first_name": "e", "date_of_birth": "11-02-1598", "gender": 0, "rang": null, "number_of_point": 0}, "22": {"name": "r", "first_name": "r", "date_of_birth": "11-11-2020", "gender": 1, "rang": null, "number_of_point": 0}, "23": {"name": "t", "first_name": "t", "date_of_birth": "11-02-2202", "gender": 1, "rang": null, "number_of_point": 0}}, "table_of_tournament": {"1": {"name": "tournoi test", "place": "pau", "date": "23-11-2022", "number_of_round": 4, "number_of_player": 8, "round_list": [], "players_list": [{"name": "fytrdtrdut", "first_name": "hhguu", "date_of_birth": "11-02-1999", "gender": 0, "rang": null, "number_of_point": 0}, {"name": "hlyguyl", "first_name": "jhu", "date_of_birth": "11-11-2022", "gender": 0, "rang": null, "number_of_point": 0}, {"name": "m", "first_name": "m", "date_of_birth": "11-02-1231", "gender": 0, "rang": null, "number_of_point": 0}, {"name": "q", "first_name": "q", "date_of_birth": "11-11-2022", "gender": 0, "rang": null, "number_of_point": 0}, {"name": "d", "first_name": "d", "date_of_birth": "11-02-1988", "gender": 0, "rang": null, "number_of_point": 0}, {"name": "z", "first_name": "z", "date_of_birth": "11-11-2525", "gender": 0, "rang": null, "number_of_point": 0}, {"name": "e", "first_name": "e", "date_of_birth": "11-02-1598", "gender": 0, "rang": null, "number_of_point": 0}, {"name": "r", "first_name": "r", "date_of_birth": "11-11-2020", "gender": 1, "rang": null, "number_of_point": 0}, {"name": "t", "first_name": "t", "date_of_birth": "11-02-2202", "gender": 1, "rang": null, "number_of_point": 0}], "time_control": "Blitz", "description": "test d enregistrement du tournoi"}}}